agiletoolkit/__init__.py
agiletoolkit/commands.py
agiletoolkit/kong.py
agiletoolkit/manager.py
agiletoolkit/repo.py
agiletoolkit/slack.py
agiletoolkit/test.py
agiletoolkit/utils.py
agiletoolkit/api/__init__.py
agiletoolkit/api/components.py
agiletoolkit/api/releases.py
agiletoolkit/api/repo.py
agiletoolkit/github/__init__.py
agiletoolkit/github/info.py
agiletoolkit/github/labels.py
agiletoolkit/github/milestones.py
agiletoolkit/github/release.py
agiletoolkit/github/remote.py
agiletoolkit/github/utils.py
agiletoolkit/github/validate.py
agile_toolkit-0.6.0.dist-info/LICENSE
agile_toolkit-0.6.0.dist-info/METADATA
agile_toolkit-0.6.0.dist-info/WHEEL
agile_toolkit-0.6.0.dist-info/entry_points.txt
agile_toolkit-0.6.0.dist-info/top_level.txt
agile_toolkit-0.6.0.dist-info/RECORD
