Metadata-Version: 2.1
Name: agile-toolkit
Version: 0.6.0
Summary: Agile toolkit for publishing and repository management
Home-page: https://github.com/quantmind/agile-toolkit
Author: Luca Sbardella
Author-email: luca@quantmind.com
Maintainer-email: luca@quantmind.com
License: UNKNOWN
Platform: UNKNOWN
Classifier: Development Status :: 3 - Alpha
Classifier: Intended Audience :: Developers
Classifier: License :: OSI Approved :: BSD License
Classifier: Operating System :: OS Independent
Classifier: Programming Language :: JavaScript
Classifier: Programming Language :: Python
Classifier: Programming Language :: Python :: 3
Classifier: Programming Language :: Python :: 3.6
Classifier: Programming Language :: Python :: 3.7
Classifier: Programming Language :: Python :: 3.8
Classifier: Topic :: Utilities
Requires-Dist: click
Requires-Dist: python-dotenv
Requires-Dist: pyyaml
Requires-Dist: requests
Requires-Dist: jinja2
Requires-Dist: slackclient
Requires-Dist: aio-kong
